  {
    "log_1": {
      "room_id": "room1",
      "rows": 3,
      "cols": 10,
      "change": [{
        "row":2,
        "col":3,
        "newtile":  {"ch":[],"mov":"","store":"","immov":"","ex":[],"kl":[],"rt":[]}
        }],
      "inv_change": ["",""],
      "chat": "",
      "cutscene": [["",""]]
    },
    "log_2": {
      "room_id": "room1",
      "rows": 3,
      "cols": 10,
      "change": [{
        "row":2,
        "col":3,
        "newtile":  {"ch":[],"mov":"","store":"","immov":"","ex":[],"kl":[],"rt":[]}
        }],
      "inv_change": ["",""],
      "chat": "",
      "cutscene": [["",""]]
    },
  }
